Metadata-Version: 2.1
Name: nepali-phone-number
Version: 0.0.2
Summary: A package for nepali mobile number
Home-page: https://github.com/sbishnu019/nepali-phone-number
Author: Bishnu Sharma
Author-email: sbishnu019@gmail.com
License: UNKNOWN
Download-URL: https://github.com/sbishnu019/nepali-phone-number/archive/v0.0.2.tar.gz
Platform: UNKNOWN
Classifier: Programming Language :: Python :: 3
Classifier: License :: OSI Approved :: MIT License
Classifier: Operating System :: OS Independent
Requires-Python: >=3.6
